wizcli/cli.py
wizcli/wiz.py
wizcli-0.1.6.dist-info/METADATA
wizcli-0.1.6.dist-info/WHEEL
wizcli-0.1.6.dist-info/entry_points.txt
wizcli-0.1.6.dist-info/RECORD
