Metadata-Version: 2.1
Name: wizcli
Version: 0.1.6
Summary: control WiZ bulbs from the CLI
Home-page: https://github.com/redraw/wizcli
Author: Agustin B
Author-email: redraw@sdf.org
Requires-Python: >=3.8,<4.0
Classifier: Programming Language :: Python :: 3
Classifier: Programming Language :: Python :: 3.8
Classifier: Programming Language :: Python :: 3.9
Classifier: Programming Language :: Python :: 3.10
Classifier: Programming Language :: Python :: 3.11
Requires-Dist: typer (>=0.7.0,<0.8.0)
Project-URL: Repository, https://github.com/redraw/wizcli
